<?xml version="1.0" encoding="utf-8" ?>
<dwsync>
<file name="Auth.class.php" server="118.123.243.249" local="131610570493920142" remote="131618629200000000" Dst="0" />
<file name="Dept.class.php" server="118.123.243.249" local="131609807906126364" remote="131618629200000000" Dst="0" />
<file name="Index.class.php" server="118.123.243.249" local="131609794865179403" remote="131618629200000000" Dst="0" />
<file name="Login.class.php" server="118.123.243.249" local="131610572718305055" remote="131618629200000000" Dst="0" />
<file name="Menu.class.php" server="118.123.243.249" local="131609796836733803" remote="131618629200000000" Dst="0" />
<file name="Position.class.php" server="118.123.243.249" local="131609812068196253" remote="131618629200000000" Dst="0" />
<file name="Method.class.php" server="118.123.243.249" local="131609802637640829" remote="131618629200000000" Dst="0" />
<file name="Role.class.php" server="118.123.243.249" local="131609811025477386" remote="131618629200000000" Dst="0" />
<file name="Sys.class.php" server="118.123.243.249" local="131609800297616056" remote="131618629200000000" Dst="0" />
<file name="SysConfig.class.php" server="118.123.243.249" local="131610817337766277" remote="131618629200000000" Dst="0" />
<file name="SysData.class.php" server="118.123.243.249" local="131609807074927158" remote="131618629200000000" Dst="0" />
<file name="SysLog.class.php" server="118.123.243.249" local="131502567078851801" remote="131618629200000000" Dst="0" />
<file name="User.class.php" server="118.123.243.249" local="131610572103154218" remote="131618629200000000" Dst="0" />
<file name="Auth.class.php" server="118.123.243.249//dggxs_com/wwwroot/" local="131621407583067453" remote="131637614400000000" Dst="0" />
<file name="Index.class.php" server="118.123.243.249//dggxs_com/wwwroot/" local="131621408076805156" remote="131637614400000000" Dst="0" />
<file name="Dept.class.php" server="118.123.243.249//dggxs_com/wwwroot/" local="131621407789691280" remote="131637614400000000" Dst="0" />
<file name="Login.class.php" server="118.123.243.249//dggxs_com/wwwroot/" local="131621408291093684" remote="131637614400000000" Dst="0" />
<file name="Menu.class.php" server="118.123.243.249//dggxs_com/wwwroot/" local="131621408607803716" remote="131637614400000000" Dst="0" />
<file name="Method.class.php" server="118.123.243.249//dggxs_com/wwwroot/" local="131621409169847269" remote="131637614400000000" Dst="0" />
<file name="Position.class.php" server="118.123.243.249//dggxs_com/wwwroot/" local="131621409385148903" remote="131637614400000000" Dst="0" />
<file name="Role.class.php" server="118.123.243.249//dggxs_com/wwwroot/" local="131621409562722117" remote="131637614400000000" Dst="0" />
<file name="Sys.class.php" server="118.123.243.249//dggxs_com/wwwroot/" local="131621409868623613" remote="131637614400000000" Dst="0" />
<file name="SysConfig.class.php" server="118.123.243.249//dggxs_com/wwwroot/" local="131621409987625286" remote="131637614400000000" Dst="0" />
<file name="SysData.class.php" server="118.123.243.249//dggxs_com/wwwroot/" local="131621410264523214" remote="131637614400000000" Dst="0" />
<file name="SysLog.class.php" server="118.123.243.249//dggxs_com/wwwroot/" local="131621410418484815" remote="131637614400000000" Dst="0" />
<file name="User.class.php" server="118.123.243.249//dggxs_com/wwwroot/" local="131621410564402821" remote="131637614400000000" Dst="0" />
<file name="Auth.class.php" server="211.149.238.19//test/wwwroot/" local="131730653745029638" remote="131731533600000000" Dst="0" />
<file name="Dept.class.php" server="211.149.238.19//test/wwwroot/" local="131730649675882980" remote="131731533600000000" Dst="0" />
<file name="Index.class.php" server="211.149.238.19//test/wwwroot/" local="131730649934874913" remote="131731533600000000" Dst="0" />
<file name="Login.class.php" server="211.149.238.19//test/wwwroot/" local="131730650010697809" remote="131731533600000000" Dst="0" />
<file name="Menu.class.php" server="211.149.238.19//test/wwwroot/" local="131730650097793863" remote="131731533600000000" Dst="0" />
<file name="Method.class.php" server="211.149.238.19//test/wwwroot/" local="131730650169623929" remote="131731533600000000" Dst="0" />
<file name="Position.class.php" server="211.149.238.19//test/wwwroot/" local="131730650235685311" remote="131731533600000000" Dst="0" />
<file name="Role.class.php" server="211.149.238.19//test/wwwroot/" local="131730650307198681" remote="131731533600000000" Dst="0" />
<file name="Sys.class.php" server="211.149.238.19//test/wwwroot/" local="131730650386285498" remote="131731533600000000" Dst="0" />
<file name="SysConfig.class.php" server="211.149.238.19//test/wwwroot/" local="131730650459637944" remote="131731533600000000" Dst="0" />
<file name="SysLog.class.php" server="211.149.238.19//test/wwwroot/" local="131730650607999524" remote="131731533600000000" Dst="0" />
<file name="User.class.php" server="211.149.238.19//test/wwwroot/" local="131730650680369576" remote="131731533600000000" Dst="0" />
<file name="SysData.class.php" server="211.149.238.19//test/wwwroot/" local="131730650535758379" remote="131731533600000000" Dst="0" />
<file name="Area.class.php" server="211.149.238.19//180710_zxtx/wwwroot/" local="131789726706862011" remote="131789718000000000" Dst="0" />
<file name="Auth.class.php" server="211.149.238.19//180710_zxtx/wwwroot/" local="131730653745029638" remote="131794811400000000" Dst="0" />
<file name="Dept.class.php" server="211.149.238.19//180710_zxtx/wwwroot/" local="131782105891042404" remote="131794811400000000" Dst="0" />
<file name="Index.class.php" server="211.149.238.19//180710_zxtx/wwwroot/" local="131781026800300477" remote="131794811400000000" Dst="0" />
<file name="Method.class.php" server="211.149.238.19//180710_zxtx/wwwroot/" local="131730650169623929" remote="131794811400000000" Dst="0" />
<file name="Login.class.php" server="211.149.238.19//180710_zxtx/wwwroot/" local="131781869160729106" remote="131794811400000000" Dst="0" />
<file name="Menu.class.php" server="211.149.238.19//180710_zxtx/wwwroot/" local="131781980258143315" remote="131794811400000000" Dst="0" />
<file name="Role.class.php" server="211.149.238.19//180710_zxtx/wwwroot/" local="131782123998764830" remote="131794811400000000" Dst="0" />
<file name="Sys.class.php" server="211.149.238.19//180710_zxtx/wwwroot/" local="131781933325781682" remote="131794811400000000" Dst="0" />
<file name="Position.class.php" server="211.149.238.19//180710_zxtx/wwwroot/" local="131782546506959500" remote="131794811400000000" Dst="0" />
<file name="SysConfig.class.php" server="211.149.238.19//180710_zxtx/wwwroot/" local="131781064457483452" remote="131794811400000000" Dst="0" />
<file name="SysData.class.php" server="211.149.238.19//180710_zxtx/wwwroot/" local="131781971594727981" remote="131794811400000000" Dst="0" />
<file name="SysLog.class.php" server="211.149.238.19//180710_zxtx/wwwroot/" local="131730650607999524" remote="131794811400000000" Dst="0" />
<file name="User.class.php" server="211.149.238.19//180710_zxtx/wwwroot/" local="131786009656145585" remote="131794811400000000" Dst="0" />
<file name="Area.class.php" server="47.92.36.4//" local="131797493535381522" remote="131797493400000000" Dst="0" />
<file name="Area.class.php" server="211.149.238.19//07fly_erp/wwwroot/" local="131879597318361853" remote="131907183000000000" Dst="0" />
<file name="Auth.class.php" server="211.149.238.19//07fly_erp/wwwroot/" local="131907201903788049" remote="131907190800000000" Dst="0" />
<file name="Dept.class.php" server="211.149.238.19//07fly_erp/wwwroot/" local="131879596953401965" remote="131907183600000000" Dst="0" />
<file name="Email.class.php" server="211.149.238.19//07fly_erp/wwwroot/" local="131880400447190410" remote="131907183600000000" Dst="0" />
<file name="EmailLog.class.php" server="211.149.238.19//07fly_erp/wwwroot/" local="131880415137078829" remote="131907183600000000" Dst="0" />
<file name="EmailMb.class.php" server="211.149.238.19//07fly_erp/wwwroot/" local="131880409389807360" remote="131907183600000000" Dst="0" />
<file name="Index.class.php" server="211.149.238.19//07fly_erp/wwwroot/" local="131888210052202682" remote="131907183600000000" Dst="0" />
<file name="Login.class.php" server="211.149.238.19//07fly_erp/wwwroot/" local="131907202688114601" remote="131907191400000000" Dst="0" />
<file name="Menu.class.php" server="211.149.238.19//07fly_erp/wwwroot/" local="131907193875145249" remote="131907183600000000" Dst="0" />
<file name="Method.class.php" server="211.149.238.19//07fly_erp/wwwroot/" local="131907026714351059" remote="131907183600000000" Dst="0" />
<file name="Position.class.php" server="211.149.238.19//07fly_erp/wwwroot/" local="131879582929733247" remote="131907183600000000" Dst="0" />
<file name="Role.class.php" server="211.149.238.19//07fly_erp/wwwroot/" local="131907193966840322" remote="131907183600000000" Dst="0" />
<file name="Sms.class.php" server="211.149.238.19//07fly_erp/wwwroot/" local="131880328465750183" remote="131907183600000000" Dst="0" />
<file name="SmsLog.class.php" server="211.149.238.19//07fly_erp/wwwroot/" local="131880412725804581" remote="131907183600000000" Dst="0" />
<file name="SmsMb.class.php" server="211.149.238.19//07fly_erp/wwwroot/" local="131880326225975691" remote="131907183600000000" Dst="0" />
<file name="Sys.class.php" server="211.149.238.19//07fly_erp/wwwroot/" local="131888222914602803" remote="131907183600000000" Dst="0" />
<file name="SysConfig.class.php" server="211.149.238.19//07fly_erp/wwwroot/" local="131781064457483452" remote="131907183600000000" Dst="0" />
<file name="SysData.class.php" server="211.149.238.19//07fly_erp/wwwroot/" local="131781971594727981" remote="131907183600000000" Dst="0" />
<file name="SysLog.class.php" server="211.149.238.19//07fly_erp/wwwroot/" local="131730650607999524" remote="131907183600000000" Dst="0" />
<file name="User.class.php" server="211.149.238.19//07fly_erp/wwwroot/" local="131904831493133850" remote="131907183600000000" Dst="0" />
</dwsync>